textsummarizer/textsummarizer.py
textsummarizer-1.0.0.dist-info/LICENSE
textsummarizer-1.0.0.dist-info/METADATA
textsummarizer-1.0.0.dist-info/WHEEL
textsummarizer-1.0.0.dist-info/top_level.txt
textsummarizer-1.0.0.dist-info/RECORD
